pysqliteog/__init__.py
pysqliteog/dbapi2.py
pysqliteog/errors.py
pysqliteog/gen/__init__.py
pysqliteog/gen/sqliteog_pb2.py
pysqliteog/gen/sqliteog_pb2.pyi
pysqliteog/gen/sqliteog_pb2_grpc.py
tests/__init__.py
tests/test_db.py
pysqliteog-0.0.5.dist-info/LICENSE
pysqliteog-0.0.5.dist-info/METADATA
pysqliteog-0.0.5.dist-info/WHEEL
pysqliteog-0.0.5.dist-info/top_level.txt
pysqliteog-0.0.5.dist-info/RECORD
