Metadata-Version: 2.1
Name: pysqliteog
Version: 0.0.5
Summary: a python DBAPI 2.0 interface for sqlite-og
Home-page: https://github.com/aousomran/pysqliteog
Author: Aous Omran
Author-email: aous.omr@gmail.com
Project-URL: Bug Tracker, https://github.com/aousomran/pysqliteog/issues
Classifier: Programming Language :: Python :: 3
Classifier: License :: OSI Approved :: MIT License
Classifier: Operating System :: OS Independent
Requires-Python: >=3.8
License-File: LICENSE
Requires-Dist: grpcio
Requires-Dist: protobuf
